src/elib/__about__.py
src/elib/__init__.py
src/elib/app.py
madskris_elib-0.6.0.dist-info/METADATA
madskris_elib-0.6.0.dist-info/WHEEL
madskris_elib-0.6.0.dist-info/licenses/LICENSE.txt
madskris_elib-0.6.0.dist-info/RECORD
