Metadata-Version: 2.3
Name: MadsKris.elib
Version: 0.6.0
Project-URL: Documentation, https://github.com/MadsKrist/elib#readme
Project-URL: Issues, https://github.com/MadsKrist/elib/issues
Project-URL: Source, https://github.com/MadsKrist/elib
Author-email: Mads Kristensen <madskris@proton.me>
License-Expression: MIT
License-File: LICENSE.txt
Classifier: Programming Language :: Python :: 3.12
Classifier: Programming Language :: Python :: Implementation :: CPython
Classifier: Programming Language :: Python :: Implementation :: PyPy
Requires-Python: >=3.12
Requires-Dist: attrs
Requires-Dist: icecream
Requires-Dist: numpy
